deepgeo/Engine.py
deepgeo/Font.py
deepgeo/Image.py
deepgeo/Log.py
deepgeo/Utils.py
deepgeo/__init__.py
deepgeo-0.2.1.dist-info/LICENSE
deepgeo-0.2.1.dist-info/METADATA
deepgeo-0.2.1.dist-info/WHEEL
deepgeo-0.2.1.dist-info/top_level.txt
deepgeo-0.2.1.dist-info/RECORD
