Metadata-Version: 2.1
Name: deepgeo
Version: 0.2.1
Summary: Easy Deep Learning
Home-page: https://github.com/Sotaneum/DeepGeo
Author: Donggun LEE
Author-email: gnyotnu39@gmail.com
License: MIT
Platform: UNKNOWN
Classifier: License :: OSI Approved :: MIT License
